{
  "bookSlug": "galatians",
  "chapters": [
    {
      "bookSlug": "galatians",
      "chapterNumber": 1,
      "verses": []
    },
    {
      "bookSlug": "galatians",
      "chapterNumber": 2,
      "verses": []
    },
    {
      "bookSlug": "galatians",
      "chapterNumber": 3,
      "verses": []
    },
    {
      "bookSlug": "galatians",
      "chapterNumber": 4,
      "verses": []
    },
    {
      "bookSlug": "galatians",
      "chapterNumber": 5,
      "verses": []
    },
    {
      "bookSlug": "galatians",
      "chapterNumber": 6,
      "verses": []
    }
  ]
}
